Metadata-Version: 2.1
Name: finalynx-assistant
Version: 0.0.1
Summary: A command line investment assistant to organize your portfolio and simulate its future to reach your life goals.
Home-page: https://github.com/MadeInPierre/finary_assistant
Author: Pierre Laclau (MadeInPierre)
Author-email: pielaclau@gmail.com
License: GNU General Public Version 3
Platform: UNKNOWN
Classifier: Development Status :: 3 - Alpha
Classifier: Environment :: Console
Classifier: Intended Audience :: End Users/Desktop
Classifier: Intended Audience :: Financial and Insurance Industry
Classifier: Intended Audience :: Information Technology
Classifier: Operating System :: OS Independent
Classifier: Programming Language :: Python
Classifier: Programming Language :: Python :: 3
Classifier: Programming Language :: Python :: 3.8
Classifier: Programming Language :: Python :: 3.9
Classifier: Programming Language :: Python :: 3.10
Classifier: Programming Language :: Python :: 3.11
Classifier: Programming Language :: Python :: 3.12
Requires-Dist: docopt (>=0.6.2)
Requires-Dist: fuzzywuzzy[speedup] (>=0.18.0)
Requires-Dist: requests (==2.28.2)
Requires-Dist: rich (>=12.0.1)
Provides-Extra: dev
Requires-Dist: black ; extra == 'dev'
Requires-Dist: pdoc3 ; extra == 'dev'
